dw2d/Dcel.py
dw2d/Geometric_utilities.py
dw2d/Graph_functions.py
dw2d/Mask_reconstruction.py
dw2d/Networkx_functions.py
dw2d/Plotting_tools.py
dw2d/__init__.py
dw2d/functions.py
delaunay_watershed_2d-0.1.5.dist-info/METADATA
delaunay_watershed_2d-0.1.5.dist-info/WHEEL
delaunay_watershed_2d-0.1.5.dist-info/top_level.txt
delaunay_watershed_2d-0.1.5.dist-info/RECORD
