Metadata-Version: 2.1
Name: delaunay-watershed-2d
Version: 0.1.5
Summary: Geometrical reconstruction of cell assemblies from instance segmentations
Home-page: https://github.com/virtualembryo/delaunay_watershed_2d
Author: Sacha Ichbiah
Author-email: sacha.ichbiah@college-de-france.fr
Project-URL: Team website, https://www.turlierlab.com/
Classifier: Programming Language :: Python :: 3
Classifier: License :: OSI Approved :: MIT License
Classifier: Operating System :: POSIX :: Linux
Classifier: Operating System :: MacOS
Classifier: License :: OSI Approved :: MIT License
Classifier: Intended Audience :: Science/Research
Requires-Python: >=3.6
Requires-Dist: scikit-image >=0.18.3
Requires-Dist: numpy >=1.21.6
Requires-Dist: scipy >=1.4.1
Requires-Dist: polyscope >=1.2.0
Requires-Dist: matplotlib >=3.3.1
Requires-Dist: networkx >=2.5.1
